LICENSE
MANIFEST.in
README.md
README.rst
setup.py
bin/tempfiles
src/tempfiles_cmdline/__init__.py
src/tempfiles_cmdline/utils.py
src/tempfiles_cmdline.egg-info/PKG-INFO
src/tempfiles_cmdline.egg-info/SOURCES.txt
src/tempfiles_cmdline.egg-info/dependency_links.txt
src/tempfiles_cmdline.egg-info/not-zip-safe
src/tempfiles_cmdline.egg-info/requires.txt
src/tempfiles_cmdline.egg-info/top_level.txt
src/tempfiles_conf/__init__.py
src/tempfiles_conf/configuration.py