Metadata-Version: 1.1
Name: tempfiles-cmdline
Version: 1.1.0
Summary: Tempfil.es ephemeral/anonymous file sharing service command line tool
Home-page: https://tempfil.es
Author: Marco Antonio Albero Albero
Author-email: marco@mybi.es
License: Apache License, Version 2.0
Keywords: ephemeral file sharing,anonymous file sharing,devops,sysadmin
Platform: UNKNOWN
Classifier: Development Status :: 5 - Production/Stable
Classifier: Intended Audience :: Developers
Classifier: Intended Audience :: System Administrators
Classifier: Natural Language :: English
Classifier: Operating System :: OS Independent
Classifier: Programming Language :: Python
Classifier: Programming Language :: Python :: Implementation :: PyPy
